LICENSE
MANIFEST.in
README.md
requirements.txt
setup.py
Py_SPW.egg-info/PKG-INFO
Py_SPW.egg-info/SOURCES.txt
Py_SPW.egg-info/dependency_links.txt
Py_SPW.egg-info/requires.txt
Py_SPW.egg-info/top_level.txt
docs/source/conf.py
examples/check_access.py
examples/check_api_work.py
examples/create_payment_link.py
examples/get_selfcard_info.py
examples/send_transaction.py
examples/users_actions.py
examples/validate_webhook.py
pyspw/__init__.py
pyspw/api.py
pyspw/errors.py
pyspw/methods/__init__.py
pyspw/methods/base.py
pyspw/methods/create_payment.py
pyspw/methods/create_transaction.py
pyspw/methods/get_me.py
pyspw/methods/get_selfcard_info.py
pyspw/methods/get_user.py
pyspw/methods/get_user_cards.py
pyspw/methods/set_transaction_webhook.py
pyspw/models/Card.py
pyspw/models/ServerAnswers.py
pyspw/models/Transaction.py
pyspw/models/User.py
pyspw/models/__init__.py