Metadata-Version: 2.1
Name: Py-SPW
Version: 2.0.0
Summary: Python library for spworlds API
Home-page: https://github.com/teleportx/Py-SPW
Author: Stepan Khozhempo
Author-email: stepan@xstl.ru
License: MIT License
Project-URL: Docs, https://pyspw.xstl.ru/en/latest/
Project-URL: GitHub, https://github.com/teleport2/Py-SPW/
Requires-Python: >=3.7
License-File: LICENSE
